{"temple event": [{"date": "2021-10-10", "district": "\u5c4f\u6771 \u7409\u7403\u9109", "temple": "\u5c0f\u7409\u7403\u4e09\u9686\u5bae", "event": "\u8fce \u5de1\u72e9 \u9076\u5883"}, {"date": "2021-10-10", "district": "\u5c4f\u6771 \u65b0\u5712\u9109", "temple": "\u9e7d\u57d4\u4ed4\u65b0\u8208\u5bae", "event": "\u9076\u5883"}, {"date": "2021-10-10", "district": "\u9ad8\u96c4 \u6a4b\u982d\u5340", "temple": "\u828b\u5bee\u58fd\u751f\u5edf", "event": "\u9032\u9999 \u56de\u99d5 \u9076\u5883"}], "version": "2021-10-09 23:55:25"}